tdg_api_connector/__init__.py
tdg_api_connector/api/__init__.py
tdg_api_connector/api/append.py
tdg_api_connector/api/lookup.py
tdg_api_connector/api/verify.py
tdg_api_connector/test/__init__.py
tdg_api_connector/test/test_append.py
tdg_api_connector/test/test_lookup.py
tdg_api_connector/test/test_verify.py
tdg_api_connector/utilities/__init__.py
tdg_api_connector/utilities/helpers.py
tdg_connector_py-0.1.1.dist-info/METADATA
tdg_connector_py-0.1.1.dist-info/WHEEL
tdg_connector_py-0.1.1.dist-info/top_level.txt
tdg_connector_py-0.1.1.dist-info/RECORD
