Metadata-Version: 2.4
Name: tdg-connector-py
Version: 0.1.1
Summary: TdgAPI Python Client
Author: Pankaj-tdg
Author-email: pankaj.gawade@truthics.com
Keywords: python
Requires-Dist: requests
Dynamic: author
Dynamic: author-email
Dynamic: description
Dynamic: description-content-type
Dynamic: keywords
Dynamic: requires-dist
Dynamic: summary
